{
  "timestamp": "2026-06-03T18:10:06.310Z",
  "summary": {
    "processed": 96,
    "converted": 77,
    "skipped": 10,
    "avifReoptimized": 2,
    "keptOriginal": 7,
    "errors": 0,
    "referencesUpdated": 136,
    "filesModified": 70,
    "filesDeleted": 77,
    "brokenReferences": 0,
    "totalSrcBytes": 29446312,
    "totalOutBytes": 8553959,
    "reductionPct": "71.0%"
  },
  "modifiedFiles": [
    "resources\\js\\script.js",
    "resources\\lang\\ar\\contact.php",
    "resources\\lang\\de\\contact.php",
    "resources\\lang\\en\\contact.php",
    "resources\\lang\\fr\\contact.php",
    "resources\\views\\auth\\login.blade.php",
    "resources\\views\\auth\\passwords\\email.blade.php",
    "resources\\views\\backoffice\\attestations\\pdf-single.blade.php",
    "resources\\views\\backoffice\\attestations\\pdf.blade.php",
    "resources\\views\\backoffice\\certificates\\pdf.blade.php",
    "resources\\views\\backoffice\\crm\\partials\\_row_modal.blade.php",
    "resources\\views\\backoffice\\crm\\partials\\_table.blade.php",
    "resources\\views\\backoffice\\level_followups\\pdf_group.blade.php",
    "resources\\views\\backoffice\\pdf\\planning-site.blade.php",
    "resources\\views\\backoffice\\pdf\\planning-week.blade.php",
    "resources\\views\\backoffice\\pdf\\planning.blade.php",
    "resources\\views\\backoffice\\pdf\\weekly-report-single.blade.php",
    "resources\\views\\backoffice\\pdf\\weekly-report.blade.php",
    "resources\\views\\backoffice\\profile\\index.blade.php",
    "resources\\views\\backoffice\\teachers\\table.blade.php",
    "resources\\views\\emails\\layouts\\branded.blade.php",
    "resources\\views\\errors\\layout.blade.php",
    "resources\\views\\frontoffice\\about.blade.php",
    "resources\\views\\frontoffice\\blog\\blog.blade.php",
    "resources\\views\\frontoffice\\discover-your-level.blade.php",
    "resources\\views\\frontoffice\\exams\\gls.blade.php",
    "resources\\views\\frontoffice\\exams\\goethe.blade.php",
    "resources\\views\\frontoffice\\exams\\osd.blade.php",
    "resources\\views\\frontoffice\\faq.blade.php",
    "resources\\views\\frontoffice\\home.blade.php",
    "resources\\views\\frontoffice\\intensive-courses.blade.php",
    "resources\\views\\frontoffice\\landing\\google.blade.php",
    "resources\\views\\frontoffice\\landing\\meta.blade.php",
    "resources\\views\\frontoffice\\layouts\\app.blade.php",
    "resources\\views\\frontoffice\\niveaux\\a1.blade.php",
    "resources\\views\\frontoffice\\niveaux\\a2.blade.php",
    "resources\\views\\frontoffice\\niveaux\\b1.blade.php",
    "resources\\views\\frontoffice\\niveaux\\b2.blade.php",
    "resources\\views\\frontoffice\\online-courses.blade.php",
    "resources\\views\\frontoffice\\partials\\seo-head.blade.php",
    "resources\\views\\frontoffice\\partials\\testimonials-videos.blade.php",
    "resources\\views\\frontoffice\\partners\\fc-marokko.blade.php",
    "resources\\views\\frontoffice\\pricing.blade.php",
    "resources\\views\\frontoffice\\resources\\student-stories.blade.php",
    "resources\\views\\frontoffice\\sites\\agadir.blade.php",
    "resources\\views\\frontoffice\\sites\\casablanca.blade.php",
    "resources\\views\\frontoffice\\sites\\kenitra.blade.php",
    "resources\\views\\frontoffice\\sites\\marrakech.blade.php",
    "resources\\views\\frontoffice\\sites\\rabat.blade.php",
    "resources\\views\\frontoffice\\sites\\sale.blade.php",
    "resources\\views\\frontoffice\\sites.blade.php",
    "resources\\views\\layouts\\authFooter.blade.php",
    "resources\\views\\layouts\\authHeader.blade.php",
    "resources\\views\\layouts\\component-footer.blade.php",
    "resources\\views\\layouts\\component-header.blade.php",
    "resources\\views\\layouts\\layout-2.blade.php",
    "resources\\views\\layouts\\layout-cre.blade.php",
    "resources\\views\\layouts\\main.blade.php",
    "resources\\views\\layouts\\sidebar-compact.blade.php",
    "resources\\views\\layouts\\sidebar-detached.blade.php",
    "resources\\views\\layouts\\sidebar-moduler.blade.php",
    "resources\\views\\layouts\\sidebar-tab.blade.php",
    "resources\\views\\layouts\\sidebar.blade.php",
    "resources\\views\\layouts\\topbar-d.blade.php",
    "resources\\views\\layouts\\topbar-detached.blade.php",
    "resources\\views\\layouts\\topbar-extended.blade.php",
    "resources\\views\\layouts\\topbar.blade.php",
    "resources\\views\\vendor\\mail\\html\\header.blade.php",
    "config\\home.php",
    "config\\seo.php"
  ],
  "keptOriginals": [
    {
      "file": "home\\gizlogo-unternehmen-de-rgb-300.webp",
      "srcSize": 25136,
      "avifSize": 30949
    },
    {
      "file": "home\\TLScontact_main.webp",
      "srcSize": 14630,
      "avifSize": 21005
    },
    {
      "file": "logo\\gls-blanc.webp",
      "srcSize": 20122,
      "avifSize": 22352
    },
    {
      "file": "sites\\agadir\\hero-agadir.webp",
      "srcSize": 281814,
      "avifSize": 292169
    },
    {
      "file": "sites\\kenitra.jpg",
      "srcSize": 121359,
      "avifSize": 135187
    },
    {
      "file": "sites\\marrakech.webp",
      "srcSize": 286792,
      "avifSize": 360482
    },
    {
      "file": "studienkollegs\\germany.webp",
      "srcSize": 128,
      "avifSize": 490
    }
  ],
  "brokenRefs": [],
  "errors": []
}